qnote/__init__.py
qnote/app.py
qnote/default.tcss
qnote/main.py
qnote/themes.py
qnote/utils.py
qnote/modes/__init__.py
qnote/modes/logs.py
qnote/modes/main.py
qnote/modes/settings.py
qnote/widgets/__init__.py
qnote/widgets/content.py
qnote/widgets/lumens.py
qnote/widgets/sidebar.py
qnote/widgets/stats.py
qnote-0.1.5.dist-info/licenses/LICENSE.md
qnote-0.1.5.dist-info/METADATA
qnote-0.1.5.dist-info/WHEEL
qnote-0.1.5.dist-info/entry_points.txt
qnote-0.1.5.dist-info/top_level.txt
qnote-0.1.5.dist-info/RECORD
