Metadata-Version: 2.4
Name: qnote
Version: 0.1.5
Summary: A terminal-based, local-first, note-taking app powered by Textual
Author-email: Piotr Daniel <piotr.daniel4@gmail.com>
License-Expression: MIT
Keywords: notes,textual,terminal,cli
Requires-Python: >=3.10
License-File: LICENSE.md
Requires-Dist: appdirs
Requires-Dist: textual
Requires-Dist: colorama==0.4.6
Requires-Dist: markdown-it-py==4.0.0
Requires-Dist: mdurl==0.1.2
Requires-Dist: Pygments==2.19.2
Requires-Dist: rich==14.2.0
Requires-Dist: shellingham==1.5.4
Requires-Dist: typer==0.20.0
Requires-Dist: typing_extensions==4.15.0
Dynamic: license-file
